cli/__init__.py
cli/cli.py
cli/utils/__init__.py
cli/utils/load.py
cli/utils/sig.py
naz/__init__.py
naz/__version__.py
naz/broker.py
naz/client.py
naz/codec.py
naz/correlater.py
naz/hooks.py
naz/log.py
naz/protocol.py
naz/ratelimiter.py
naz/sequence.py
naz/state.py
naz/throttle.py
naz-0.8.1.dist-info/LICENSE.txt
naz-0.8.1.dist-info/METADATA
naz-0.8.1.dist-info/WHEEL
naz-0.8.1.dist-info/entry_points.txt
naz-0.8.1.dist-info/top_level.txt
naz-0.8.1.dist-info/RECORD
