Metadata-Version: 2.1
Name: naz
Version: 0.8.1
Summary: Naz is an async SMPP client.
Home-page: https://github.com/komuw/naz
Author: komuW
Author-email: komuw05@gmail.com
License: MIT
Keywords: naz,smpp,smpp-client,smpp-protocol,smpp-library
Platform: UNKNOWN
Classifier: Development Status :: 4 - Beta
Classifier: Intended Audience :: Developers
Classifier: Topic :: Software Development :: Build Tools
Classifier: Topic :: Internet :: WWW/HTTP
Classifier: Topic :: Security
Classifier: Topic :: System :: Installation/Setup
Classifier: Topic :: System :: Networking
Classifier: Topic :: System :: Systems Administration
Classifier: Topic :: Utilities
Classifier: License :: OSI Approved :: MIT License
Classifier: Programming Language :: Python :: 3.7
Provides-Extra: benchmarks
Requires-Dist: asyncpg (==0.18.3) ; extra == 'benchmarks'
Requires-Dist: docker (==4.2.0) ; extra == 'benchmarks'
Requires-Dist: prometheus-client (==0.6.0) ; extra == 'benchmarks'
Requires-Dist: aioredis (==1.2.0) ; extra == 'benchmarks'
Requires-Dist: pythonfuzz (==1.0.3) ; extra == 'benchmarks'
Provides-Extra: dev
Requires-Dist: coverage ; extra == 'dev'
Requires-Dist: pypandoc ; extra == 'dev'
Requires-Dist: twine ; extra == 'dev'
Requires-Dist: wheel ; extra == 'dev'
Requires-Dist: Sphinx (==2.2.0) ; extra == 'dev'
Requires-Dist: sphinx-autodoc-typehints (==1.7.0) ; extra == 'dev'
Requires-Dist: sphinx-rtd-theme (==0.4.3) ; extra == 'dev'
Requires-Dist: redis (==3.2.1) ; extra == 'dev'
Requires-Dist: pika (==1.0.1) ; extra == 'dev'
Provides-Extra: test
Requires-Dist: flake8 ; extra == 'test'
Requires-Dist: pylint ; extra == 'test'
Requires-Dist: black (==19.10b0) ; extra == 'test'
Requires-Dist: bandit ; extra == 'test'
Requires-Dist: mypy ; extra == 'test'
Requires-Dist: pytype ; extra == 'test'
Requires-Dist: docker (==4.2.0) ; extra == 'test'
